{"type":"FeatureCollection", "features": [
{"type":"Feature","geometry":{"type":"Point","coordinates":[35.33368253000003,36.98451447100007]},"properties":{"id":1,"adm1_tr":"ADANA","adm1_en":"ADANA","adm0_tr":"TÜRKİYE","adm0_en":"TURKEY","pcode":"TUR001","latitude":36.984514471,"longitude":35.33368253}},
{"type":"Feature","geometry":{"type":"Point","coordinates":[38.276762216000066,37.766009163000035]},"properties":{"id":3,"adm1_tr":"ADIYAMAN","adm1_en":"ADIYAMAN","adm0_tr":"TÜRKİYE","adm0_en":"TURKEY","pcode":"TUR002","latitude":37.766009163,"longitude":38.276762216}},
{"type":"Feature","geometry":{"type":"Point","coordinates":[30.536847642000055,38.75811821800005]},"properties":{"id":5,"adm1_tr":"AFYONKARAHİSAR","adm1_en":"AFYONKARAHISAR","adm0_tr":"TÜRKİYE","adm0_en":"TURKEY","pcode":"TUR003","latitude":38.758118218,"longitude":30.536847642}},
{"type":"Feature","geometry":{"type":"Point","coordinates":[43.05036197600003,39.719443144000024]},"properties":{"id":7,"adm1_tr":"AĞRI","adm1_en":"AGRI","adm0_tr":"TÜRKİYE","adm0_en":"TURKEY","pcode":"TUR004","latitude":39.719443144,"longitude":43.050361976}},
{"type":"Feature","geometry":{"type":"Point","coordinates":[34.02709786600008,38.37134316100003]},"properties":{"id":135,"adm1_tr":"AKSARAY","adm1_en":"AKSARAY","adm0_tr":"TÜRKİYE","adm0_en":"TURKEY","pcode":"TUR068","latitude":38.371343161,"longitude":34.027097866}},
{"type":"Feature","geometry":{"type":"Point","coordinates":[35.833375025000066,40.65100329000006]},"properties":{"id":9,"adm1_tr":"AMASYA","adm1_en":"AMASYA","adm0_tr":"TÜRKİYE","adm0_en":"TURKEY","pcode":"TUR005","latitude":40.65100329,"longitude":35.833375025}},
{"type":"Feature","geometry":{"type":"Point","coordinates":[32.852915248000045,39.929794281000056]},"properties":{"id":11,"adm1_tr":"ANKARA","adm1_en":"ANKARA","adm0_tr":"TÜRKİYE","adm0_en":"TURKEY","pcode":"TUR006","latitude":39.929794281,"longitude":32.852915248}},
{"type":"Feature","geometry":{"type":"Point","coordinates":[30.70400933700006,36.88908647000005]},"properties":{"id":13,"adm1_tr":"ANTALYA","adm1_en":"ANTALYA","adm0_tr":"TÜRKİYE","adm0_en":"TURKEY","pcode":"TUR007","latitude":36.88908647,"longitude":30.704009337}},
{"type":"Feature","geometry":{"type":"Point","coordinates":[42.70139050300003,41.11365645500007]},"properties":{"id":149,"adm1_tr":"ARDAHAN","adm1_en":"ARDAHAN","adm0_tr":"TÜRKİYE","adm0_en":"TURKEY","pcode":"TUR075","latitude":41.113656455,"longitude":42.701390503}},
{"type":"Feature","geometry":{"type":"Point","coordinates":[41.82084914400008,41.18111973800006]},"properties":{"id":15,"adm1_tr":"ARTVİN","adm1_en":"ARTVIN","adm0_tr":"TÜRKİYE","adm0_en":"TURKEY","pcode":"TUR008","latitude":41.181119738,"longitude":41.820849144}},
{"type":"Feature","geometry":{"type":"Point","coordinates":[27.843431130000056,37.84879243700004]},"properties":{"id":17,"adm1_tr":"AYDIN","adm1_en":"AYDIN","adm0_tr":"TÜRKİYE","adm0_en":"TURKEY","pcode":"TUR009","latitude":37.848792437,"longitude":27.84343113}},
{"type":"Feature","geometry":{"type":"Point","coordinates":[27.873988801000053,39.63782244300006]},"properties":{"id":19,"adm1_tr":"BALIKESİR","adm1_en":"BALIKESIR","adm0_tr":"TÜRKİYE","adm0_en":"TURKEY","pcode":"TUR010","latitude":39.637822443,"longitude":27.873988801}},
{"type":"Feature","geometry":{"type":"Point","coordinates":[32.33739465700006,41.63366210700008]},"properties":{"id":147,"adm1_tr":"BARTIN","adm1_en":"BARTIN","adm0_tr":"TÜRKİYE","adm0_en":"TURKEY","pcode":"TUR074","latitude":41.633662107,"longitude":32.337394657}},
{"type":"Feature","geometry":{"type":"Point","coordinates":[41.11442346500007,37.87676169700006]},"properties":{"id":143,"adm1_tr":"BATMAN","adm1_en":"BATMAN","adm0_tr":"TÜRKİYE","adm0_en":"TURKEY","pcode":"TUR072","latitude":37.876761697,"longitude":41.114423465}},
{"type":"Feature","geometry":{"type":"Point","coordinates":[40.225088492000054,40.25809710100003]},"properties":{"id":137,"adm1_tr":"BAYBURT","adm1_en":"BAYBURT","adm0_tr":"TÜRKİYE","adm0_en":"TURKEY","pcode":"TUR069","latitude":40.258097101,"longitude":40.225088492}},
{"type":"Feature","geometry":{"type":"Point","coordinates":[29.980634904000055,40.14392000300006]},"properties":{"id":21,"adm1_tr":"BİLECİK","adm1_en":"BILECIK","adm0_tr":"TÜRKİYE","adm0_en":"TURKEY","pcode":"TUR011","latitude":40.143920003,"longitude":29.980634904}},
{"type":"Feature","geometry":{"type":"Point","coordinates":[40.49685277700007,38.88471498200005]},"properties":{"id":23,"adm1_tr":"BİNGÖL","adm1_en":"BINGOL","adm0_tr":"TÜRKİYE","adm0_en":"TURKEY","pcode":"TUR012","latitude":38.884714982,"longitude":40.496852777}},
{"type":"Feature","geometry":{"type":"Point","coordinates":[42.10763706900008,38.40435467900005]},"properties":{"id":25,"adm1_tr":"BİTLİS","adm1_en":"BITLIS","adm0_tr":"TÜRKİYE","adm0_en":"TURKEY","pcode":"TUR013","latitude":38.404354679,"longitude":42.107637069}},
{"type":"Feature","geometry":{"type":"Point","coordinates":[31.60296463900005,40.73318242700003]},"properties":{"id":27,"adm1_tr":"BOLU","adm1_en":"BOLU","adm0_tr":"TÜRKİYE","adm0_en":"TURKEY","pcode":"TUR014","latitude":40.733182427,"longitude":31.602964639}},
{"type":"Feature","geometry":{"type":"Point","coordinates":[30.28323695000006,37.72041588500008]},"properties":{"id":29,"adm1_tr":"BURDUR","adm1_en":"BURDUR","adm0_tr":"TÜRKİYE","adm0_en":"TURKEY","pcode":"TUR015","latitude":37.720415885,"longitude":30.28323695}},
{"type":"Feature","geometry":{"type":"Point","coordinates":[29.058915786000057,40.196500796000066]},"properties":{"id":31,"adm1_tr":"BURSA","adm1_en":"BURSA","adm0_tr":"TÜRKİYE","adm0_en":"TURKEY","pcode":"TUR016","latitude":40.196500796,"longitude":29.058915786}},
{"type":"Feature","geometry":{"type":"Point","coordinates":[26.406293660000074,40.14649806500006]},"properties":{"id":33,"adm1_tr":"ÇANAKKALE","adm1_en":"CANAKKALE","adm0_tr":"TÜRKİYE","adm0_en":"TURKEY","pcode":"TUR017","latitude":40.146498065,"longitude":26.40629366}},
{"type":"Feature","geometry":{"type":"Point","coordinates":[33.61636770500007,40.599663417000045]},"properties":{"id":35,"adm1_tr":"ÇANKIRI","adm1_en":"CANKIRI","adm0_tr":"TÜRKİYE","adm0_en":"TURKEY","pcode":"TUR018","latitude":40.599663417,"longitude":33.616367705}},
{"type":"Feature","geometry":{"type":"Point","coordinates":[34.95497357600004,40.55039135700008]},"properties":{"id":37,"adm1_tr":"ÇORUM","adm1_en":"CORUM","adm0_tr":"TÜRKİYE","adm0_en":"TURKEY","pcode":"TUR019","latitude":40.550391357,"longitude":34.954973576}},
{"type":"Feature","geometry":{"type":"Point","coordinates":[29.086035460000062,37.78175477900004]},"properties":{"id":39,"adm1_tr":"DENİZLİ","adm1_en":"DENIZLI","adm0_tr":"TÜRKİYE","adm0_en":"TURKEY","pcode":"TUR020","latitude":37.781754779,"longitude":29.08603546}},
{"type":"Feature","geometry":{"type":"Point","coordinates":[40.217212526000026,37.913629101000026]},"properties":{"id":41,"adm1_tr":"DİYARBAKIR","adm1_en":"DIYARBAKIR","adm0_tr":"TÜRKİYE","adm0_en":"TURKEY","pcode":"TUR021","latitude":37.913629101,"longitude":40.217212526}},
{"type":"Feature","geometry":{"type":"Point","coordinates":[31.163861362000034,40.83947626600008]},"properties":{"id":161,"adm1_tr":"DÜZCE","adm1_en":"DUZCE","adm0_tr":"TÜRKİYE","adm0_en":"TURKEY","pcode":"TUR081","latitude":40.839476266,"longitude":31.163861362}},
{"type":"Feature","geometry":{"type":"Point","coordinates":[26.552412461000074,41.67642478100004]},"properties":{"id":43,"adm1_tr":"EDİRNE","adm1_en":"EDIRNE","adm0_tr":"TÜRKİYE","adm0_en":"TURKEY","pcode":"TUR022","latitude":41.676424781,"longitude":26.552412461}},
{"type":"Feature","geometry":{"type":"Point","coordinates":[39.22912261300007,38.67313150200005]},"properties":{"id":45,"adm1_tr":"ELAZIĞ","adm1_en":"ELAZIG","adm0_tr":"TÜRKİYE","adm0_en":"TURKEY","pcode":"TUR023","latitude":38.673131502,"longitude":39.229122613}},
{"type":"Feature","geometry":{"type":"Point","coordinates":[39.47915161000003,39.74846808800004]},"properties":{"id":47,"adm1_tr":"ERZİNCAN","adm1_en":"ERZINCAN","adm0_tr":"TÜRKİYE","adm0_en":"TURKEY","pcode":"TUR024","latitude":39.748468088,"longitude":39.47915161}},
{"type":"Feature","geometry":{"type":"Point","coordinates":[41.27401457700006,39.906163839000044]},"properties":{"id":49,"adm1_tr":"ERZURUM","adm1_en":"ERZURUM","adm0_tr":"TÜRKİYE","adm0_en":"TURKEY","pcode":"TUR025","latitude":39.906163839,"longitude":41.274014577}},
{"type":"Feature","geometry":{"type":"Point","coordinates":[30.513342170000044,39.76763184400005]},"properties":{"id":51,"adm1_tr":"ESKİŞEHİR","adm1_en":"ESKISEHIR","adm0_tr":"TÜRKİYE","adm0_en":"TURKEY","pcode":"TUR026","latitude":39.767631844,"longitude":30.51334217}},
{"type":"Feature","geometry":{"type":"Point","coordinates":[37.36916828600005,37.06144922800007]},"properties":{"id":53,"adm1_tr":"GAZİANTEP","adm1_en":"GAZIANTEP","adm0_tr":"TÜRKİYE","adm0_en":"TURKEY","pcode":"TUR027","latitude":37.061449228,"longitude":37.369168286}},
{"type":"Feature","geometry":{"type":"Point","coordinates":[38.38601513500004,40.91947922300005]},"properties":{"id":55,"adm1_tr":"GİRESUN","adm1_en":"GIRESUN","adm0_tr":"TÜRKİYE","adm0_en":"TURKEY","pcode":"TUR028","latitude":40.919479223,"longitude":38.386015135}},
{"type":"Feature","geometry":{"type":"Point","coordinates":[39.47826124100004,40.45842723700008]},"properties":{"id":57,"adm1_tr":"GÜMÜŞHANE","adm1_en":"GUMUSHANE","adm0_tr":"TÜRKİYE","adm0_en":"TURKEY","pcode":"TUR029","latitude":40.458427237,"longitude":39.478261241}},
{"type":"Feature","geometry":{"type":"Point","coordinates":[43.73766663600003,37.57564813300007]},"properties":{"id":59,"adm1_tr":"HAKKARİ","adm1_en":"HAKKARI","adm0_tr":"TÜRKİYE","adm0_en":"TURKEY","pcode":"TUR030","latitude":37.575648133,"longitude":43.737666636}},
{"type":"Feature","geometry":{"type":"Point","coordinates":[36.158889282000075,36.19888195300007]},"properties":{"id":61,"adm1_tr":"HATAY","adm1_en":"HATAY","adm0_tr":"TÜRKİYE","adm0_en":"TURKEY","pcode":"TUR031","latitude":36.198881953,"longitude":36.158889282}},
{"type":"Feature","geometry":{"type":"Point","coordinates":[44.045504564000055,39.922943702000055]},"properties":{"id":151,"adm1_tr":"IĞDIR","adm1_en":"IGDIR","adm0_tr":"TÜRKİYE","adm0_en":"TURKEY","pcode":"TUR076","latitude":39.922943702,"longitude":44.045504564}},
{"type":"Feature","geometry":{"type":"Point","coordinates":[30.548083160000033,37.75921425400003]},"properties":{"id":63,"adm1_tr":"ISPARTA","adm1_en":"ISPARTA","adm0_tr":"TÜRKİYE","adm0_en":"TURKEY","pcode":"TUR032","latitude":37.759214254,"longitude":30.54808316}},
{"type":"Feature","geometry":{"type":"Point","coordinates":[28.97589975300008,41.01227385000004]},"properties":{"id":67,"adm1_tr":"İSTANBUL","adm1_en":"ISTANBUL","adm0_tr":"TÜRKİYE","adm0_en":"TURKEY","pcode":"TUR034","latitude":41.01227385,"longitude":28.975899753}},
{"type":"Feature","geometry":{"type":"Point","coordinates":[27.17186611300008,38.43414427600004]},"properties":{"id":69,"adm1_tr":"İZMİR","adm1_en":"IZMIR","adm0_tr":"TÜRKİYE","adm0_en":"TURKEY","pcode":"TUR035","latitude":38.434144276,"longitude":27.171866113}},
{"type":"Feature","geometry":{"type":"Point","coordinates":[36.92770392500006,37.57726007800005]},"properties":{"id":91,"adm1_tr":"KAHRAMANMARAŞ","adm1_en":"KAHRAMANMARAS","adm0_tr":"TÜRKİYE","adm0_en":"TURKEY","pcode":"TUR046","latitude":37.577260078,"longitude":36.927703925}},
{"type":"Feature","geometry":{"type":"Point","coordinates":[32.60845459900003,41.19591662500005]},"properties":{"id":155,"adm1_tr":"KARABÜK","adm1_en":"KARABUK","adm0_tr":"TÜRKİYE","adm0_en":"TURKEY","pcode":"TUR078","latitude":41.195916625,"longitude":32.608454599}},
{"type":"Feature","geometry":{"type":"Point","coordinates":[33.215985096000054,37.182750224000074]},"properties":{"id":139,"adm1_tr":"KARAMAN","adm1_en":"KARAMAN","adm0_tr":"TÜRKİYE","adm0_en":"TURKEY","pcode":"TUR070","latitude":37.182750224,"longitude":33.215985096}},
{"type":"Feature","geometry":{"type":"Point","coordinates":[43.09507855700008,40.60288963800008]},"properties":{"id":71,"adm1_tr":"KARS","adm1_en":"KARS","adm0_tr":"TÜRKİYE","adm0_en":"TURKEY","pcode":"TUR036","latitude":40.602889638,"longitude":43.095078557}},
{"type":"Feature","geometry":{"type":"Point","coordinates":[33.77874953200006,41.37577072900007]},"properties":{"id":73,"adm1_tr":"KASTAMONU","adm1_en":"KASTAMONU","adm0_tr":"TÜRKİYE","adm0_en":"TURKEY","pcode":"TUR037","latitude":41.375770729,"longitude":33.778749532}},
{"type":"Feature","geometry":{"type":"Point","coordinates":[35.48863447300005,38.72229228500004]},"properties":{"id":75,"adm1_tr":"KAYSERİ","adm1_en":"KAYSERI","adm0_tr":"TÜRKİYE","adm0_en":"TURKEY","pcode":"TUR038","latitude":38.722292285,"longitude":35.488634473}},
{"type":"Feature","geometry":{"type":"Point","coordinates":[37.113334794000025,36.71557646900004]},"properties":{"id":157,"adm1_tr":"KİLİS","adm1_en":"KILIS","adm0_tr":"TÜRKİYE","adm0_en":"TURKEY","pcode":"TUR079","latitude":36.715576469,"longitude":37.113334794}},
{"type":"Feature","geometry":{"type":"Point","coordinates":[33.50399372500004,39.839958540000055]},"properties":{"id":141,"adm1_tr":"KIRIKKALE","adm1_en":"KIRIKKALE","adm0_tr":"TÜRKİYE","adm0_en":"TURKEY","pcode":"TUR071","latitude":39.83995854,"longitude":33.503993725}},
{"type":"Feature","geometry":{"type":"Point","coordinates":[27.218857392000075,41.735924124000064]},"properties":{"id":77,"adm1_tr":"KIRKLARELİ","adm1_en":"KIRKLARELI","adm0_tr":"TÜRKİYE","adm0_en":"TURKEY","pcode":"TUR039","latitude":41.735924124,"longitude":27.218857392}},
{"type":"Feature","geometry":{"type":"Point","coordinates":[34.159772899000075,39.14642721800004]},"properties":{"id":79,"adm1_tr":"KIRŞEHİR","adm1_en":"KIRSEHIR","adm0_tr":"TÜRKİYE","adm0_en":"TURKEY","pcode":"TUR040","latitude":39.146427218,"longitude":34.159772899}},
{"type":"Feature","geometry":{"type":"Point","coordinates":[29.921617508000054,40.76475125400003]},"properties":{"id":81,"adm1_tr":"KOCAELİ","adm1_en":"KOCAELI","adm0_tr":"TÜRKİYE","adm0_en":"TURKEY","pcode":"TUR041","latitude":40.764751254,"longitude":29.921617508}},
{"type":"Feature","geometry":{"type":"Point","coordinates":[32.49598143600008,37.87230951600003]},"properties":{"id":83,"adm1_tr":"KONYA","adm1_en":"KONYA","adm0_tr":"TÜRKİYE","adm0_en":"TURKEY","pcode":"TUR042","latitude":37.872309516,"longitude":32.495981436}},
{"type":"Feature","geometry":{"type":"Point","coordinates":[29.98437311200007,39.41958513000003]},"properties":{"id":85,"adm1_tr":"KÜTAHYA","adm1_en":"KUTAHYA","adm0_tr":"TÜRKİYE","adm0_en":"TURKEY","pcode":"TUR043","latitude":39.41958513,"longitude":29.984373112}},
{"type":"Feature","geometry":{"type":"Point","coordinates":[38.313446372000044,38.341499644000066]},"properties":{"id":87,"adm1_tr":"MALATYA","adm1_en":"MALATYA","adm0_tr":"TÜRKİYE","adm0_en":"TURKEY","pcode":"TUR044","latitude":38.341499644,"longitude":38.313446372}},
{"type":"Feature","geometry":{"type":"Point","coordinates":[27.433656564000046,38.62226990000005]},"properties":{"id":89,"adm1_tr":"MANİSA","adm1_en":"MANISA","adm0_tr":"TÜRKİYE","adm0_en":"TURKEY","pcode":"TUR045","latitude":38.6222699,"longitude":27.433656564}},
{"type":"Feature","geometry":{"type":"Point","coordinates":[40.73778710000005,37.31228804400007]},"properties":{"id":93,"adm1_tr":"MARDİN","adm1_en":"MARDIN","adm0_tr":"TÜRKİYE","adm0_en":"TURKEY","pcode":"TUR047","latitude":37.312288044,"longitude":40.7377871}},
{"type":"Feature","geometry":{"type":"Point","coordinates":[34.63377525200008,36.801252101000046]},"properties":{"id":65,"adm1_tr":"MERSİN","adm1_en":"MERSIN","adm0_tr":"TÜRKİYE","adm0_en":"TURKEY","pcode":"TUR033","latitude":36.801252101,"longitude":34.633775252}},
{"type":"Feature","geometry":{"type":"Point","coordinates":[28.362621149000063,37.215966224000056]},"properties":{"id":95,"adm1_tr":"MUĞLA","adm1_en":"MUGLA","adm0_tr":"TÜRKİYE","adm0_en":"TURKEY","pcode":"TUR048","latitude":37.215966224,"longitude":28.362621149}},
{"type":"Feature","geometry":{"type":"Point","coordinates":[41.48897826600006,38.732195868000076]},"properties":{"id":97,"adm1_tr":"MUŞ","adm1_en":"MUS","adm0_tr":"TÜRKİYE","adm0_en":"TURKEY","pcode":"TUR049","latitude":38.732195868,"longitude":41.488978266}},
{"type":"Feature","geometry":{"type":"Point","coordinates":[34.72325927400004,38.62957599600003]},"properties":{"id":99,"adm1_tr":"NEVŞEHİR","adm1_en":"NEVSEHIR","adm0_tr":"TÜRKİYE","adm0_en":"TURKEY","pcode":"TUR050","latitude":38.629575996,"longitude":34.723259274}},
{"type":"Feature","geometry":{"type":"Point","coordinates":[34.67665249600003,37.970042386000046]},"properties":{"id":101,"adm1_tr":"NİĞDE","adm1_en":"NIGDE","adm0_tr":"TÜRKİYE","adm0_en":"TURKEY","pcode":"TUR051","latitude":37.970042386,"longitude":34.676652496}},
{"type":"Feature","geometry":{"type":"Point","coordinates":[37.87781116900004,40.98442574200004]},"properties":{"id":103,"adm1_tr":"ORDU","adm1_en":"ORDU","adm0_tr":"TÜRKİYE","adm0_en":"TURKEY","pcode":"TUR052","latitude":40.984425742,"longitude":37.877811169}},
{"type":"Feature","geometry":{"type":"Point","coordinates":[36.24845486300006,37.07503179400004]},"properties":{"id":159,"adm1_tr":"OSMANİYE","adm1_en":"OSMANIYE","adm0_tr":"TÜRKİYE","adm0_en":"TURKEY","pcode":"TUR080","latitude":37.075031794,"longitude":36.248454863}},
{"type":"Feature","geometry":{"type":"Point","coordinates":[40.52051182300005,41.023848817000044]},"properties":{"id":105,"adm1_tr":"RİZE","adm1_en":"RIZE","adm0_tr":"TÜRKİYE","adm0_en":"TURKEY","pcode":"TUR053","latitude":41.023848817,"longitude":40.520511823}},
{"type":"Feature","geometry":{"type":"Point","coordinates":[30.399985688000072,40.78055730600005]},"properties":{"id":107,"adm1_tr":"SAKARYA","adm1_en":"SAKARYA","adm0_tr":"TÜRKİYE","adm0_en":"TURKEY","pcode":"TUR054","latitude":40.780557306,"longitude":30.399985688}},
{"type":"Feature","geometry":{"type":"Point","coordinates":[36.33806222800007,41.28983163100003]},"properties":{"id":109,"adm1_tr":"SAMSUN","adm1_en":"SAMSUN","adm0_tr":"TÜRKİYE","adm0_en":"TURKEY","pcode":"TUR055","latitude":41.289831631,"longitude":36.338062228}},
{"type":"Feature","geometry":{"type":"Point","coordinates":[41.94277963600007,37.925359908000075]},"properties":{"id":111,"adm1_tr":"SİİRT","adm1_en":"SIIRT","adm0_tr":"TÜRKİYE","adm0_en":"TURKEY","pcode":"TUR056","latitude":37.925359908,"longitude":41.942779636}},
{"type":"Feature","geometry":{"type":"Point","coordinates":[35.151964511000074,42.02687075800003]},"properties":{"id":113,"adm1_tr":"SİNOP","adm1_en":"SINOP","adm0_tr":"TÜRKİYE","adm0_en":"TURKEY","pcode":"TUR057","latitude":42.026870758,"longitude":35.151964511}},
{"type":"Feature","geometry":{"type":"Point","coordinates":[37.01579997300007,39.75028772500008]},"properties":{"id":115,"adm1_tr":"SİVAS","adm1_en":"SIVAS","adm0_tr":"TÜRKİYE","adm0_en":"TURKEY","pcode":"TUR058","latitude":39.750287725,"longitude":37.015799973}},
{"type":"Feature","geometry":{"type":"Point","coordinates":[38.786037934000035,37.15359455500004]},"properties":{"id":125,"adm1_tr":"ŞANLIURFA","adm1_en":"SANLIURFA","adm0_tr":"TÜRKİYE","adm0_en":"TURKEY","pcode":"TUR063","latitude":37.153594555,"longitude":38.786037934}},
{"type":"Feature","geometry":{"type":"Point","coordinates":[42.456756074000054,37.52225849400003]},"properties":{"id":145,"adm1_tr":"ŞIRNAK","adm1_en":"SIRNAK","adm0_tr":"TÜRKİYE","adm0_en":"TURKEY","pcode":"TUR073","latitude":37.522258494,"longitude":42.456756074}},
{"type":"Feature","geometry":{"type":"Point","coordinates":[27.50939091300006,40.97555583700006]},"properties":{"id":117,"adm1_tr":"TEKİRDAĞ","adm1_en":"TEKIRDAG","adm0_tr":"TÜRKİYE","adm0_en":"TURKEY","pcode":"TUR059","latitude":40.975555837,"longitude":27.509390913}},
{"type":"Feature","geometry":{"type":"Point","coordinates":[36.55247372600007,40.31414500600005]},"properties":{"id":119,"adm1_tr":"TOKAT","adm1_en":"TOKAT","adm0_tr":"TÜRKİYE","adm0_en":"TURKEY","pcode":"TUR060","latitude":40.314145006,"longitude":36.552473726}},
{"type":"Feature","geometry":{"type":"Point","coordinates":[39.70216635200006,41.00312506000006]},"properties":{"id":121,"adm1_tr":"TRABZON","adm1_en":"TRABZON","adm0_tr":"TÜRKİYE","adm0_en":"TURKEY","pcode":"TUR061","latitude":41.00312506,"longitude":39.702166352}},
{"type":"Feature","geometry":{"type":"Point","coordinates":[39.54622317900004,39.10720682700003]},"properties":{"id":123,"adm1_tr":"TUNCELİ","adm1_en":"TUNCELI","adm0_tr":"TÜRKİYE","adm0_en":"TURKEY","pcode":"TUR062","latitude":39.107206827,"longitude":39.546223179}},
{"type":"Feature","geometry":{"type":"Point","coordinates":[29.402250989000038,38.670292946000075]},"properties":{"id":127,"adm1_tr":"UŞAK","adm1_en":"USAK","adm0_tr":"TÜRKİYE","adm0_en":"TURKEY","pcode":"TUR064","latitude":38.670292946,"longitude":29.402250989}},
{"type":"Feature","geometry":{"type":"Point","coordinates":[43.395408908000036,38.50163730000003]},"properties":{"id":129,"adm1_tr":"VAN","adm1_en":"VAN","adm0_tr":"TÜRKİYE","adm0_en":"TURKEY","pcode":"TUR065","latitude":38.5016373,"longitude":43.395408908}},
{"type":"Feature","geometry":{"type":"Point","coordinates":[29.271081193000043,40.65554241500007]},"properties":{"id":153,"adm1_tr":"YALOVA","adm1_en":"YALOVA","adm0_tr":"TÜRKİYE","adm0_en":"TURKEY","pcode":"TUR077","latitude":40.655542415,"longitude":29.271081193}},
{"type":"Feature","geometry":{"type":"Point","coordinates":[34.807623242000034,39.82322196600006]},"properties":{"id":131,"adm1_tr":"YOZGAT","adm1_en":"YOZGAT","adm0_tr":"TÜRKİYE","adm0_en":"TURKEY","pcode":"TUR066","latitude":39.823221966,"longitude":34.807623242}},
{"type":"Feature","geometry":{"type":"Point","coordinates":[31.78191540100005,41.45203208600003]},"properties":{"id":133,"adm1_tr":"ZONGULDAK","adm1_en":"ZONGULDAK","adm0_tr":"TÜRKİYE","adm0_en":"TURKEY","pcode":"TUR067","latitude":41.452032086,"longitude":31.781915401}}
]}